AUTHORS
LICENSE
README
setup.py
zpoolparty/__init__.py
zpoolparty/argv.py
zpoolparty/invoke.py
zpoolparty/util.py
zpoolparty.egg-info/PKG-INFO
zpoolparty.egg-info/SOURCES.txt
zpoolparty.egg-info/dependency_links.txt
zpoolparty.egg-info/entry_points.txt
zpoolparty.egg-info/requires.txt
zpoolparty.egg-info/top_level.txt